{
    "status": "ok",
    "message": "",
    "data": {
        "data": [
            {
                "registrants": 89491,
                "scheduledInitial": 2474,
                "scheduledBooster": 7054,
                "atLeastOneShot": 72372,
                "fullyVaccinated": 60285,
                "phase": "2"
            },
            {
                "registrants": 39193,
                "scheduledInitial": 116,
                "scheduledBooster": 265,
                "atLeastOneShot": 35238,
                "fullyVaccinated": 33458,
                "phase": "1B-1"
            },
            {
                "registrants": 44018,
                "scheduledInitial": 332,
                "scheduledBooster": 800,
                "atLeastOneShot": 40553,
                "fullyVaccinated": 38152,
                "phase": "1A"
            },
            {
                "registrants": 21171,
                "scheduledInitial": 10,
                "scheduledBooster": 41,
                "atLeastOneShot": 20404,
                "fullyVaccinated": 19932,
                "phase": "1B-0A"
            },
            {
                "registrants": 124273,
                "scheduledInitial": 924,
                "scheduledBooster": 1654,
                "atLeastOneShot": 112902,
                "fullyVaccinated": 106153,
                "phase": "1B-2"
            },
            {
                "registrants": 25107,
                "scheduledInitial": 223,
                "scheduledBooster": 650,
                "atLeastOneShot": 21552,
                "fullyVaccinated": 19162,
                "phase": "1C-1"
            },
            {
                "registrants": 39518,
                "scheduledInitial": 726,
                "scheduledBooster": 1464,
                "atLeastOneShot": 34118,
                "fullyVaccinated": 30745,
                "phase": "1C-2"
            },
            {
                "registrants": 14869,
                "scheduledInitial": 261,
                "scheduledBooster": 502,
                "atLeastOneShot": 12733,
                "fullyVaccinated": 11580,
                "phase": "1B-3B"
            },
            {
                "registrants": 5734,
                "scheduledInitial": 120,
                "scheduledBooster": 195,
                "atLeastOneShot": 4951,
                "fullyVaccinated": 4496,
                "phase": "1B-3A"
            },
            {
                "registrants": 10404,
                "scheduledInitial": 122,
                "scheduledBooster": 238,
                "atLeastOneShot": 9383,
                "fullyVaccinated": 8392,
                "phase": "1B-3C"
            },
            {
                "registrants": 5918,
                "scheduledInitial": 104,
                "scheduledBooster": 229,
                "atLeastOneShot": 5162,
                "fullyVaccinated": 4650,
                "phase": "1B-0B"
            }
        ],
        "updated": 1631652283010
    }
}