{
    "status": "ok",
    "message": "",
    "data": {
        "data": [
            {
                "registrants": 99183,
                "scheduledInitial": 4957,
                "scheduledBooster": 4219,
                "atLeastOneShot": 80569,
                "fullyVaccinated": 71114,
                "phase": "2"
            },
            {
                "registrants": 40678,
                "scheduledInitial": 110,
                "scheduledBooster": 193,
                "atLeastOneShot": 37408,
                "fullyVaccinated": 36018,
                "phase": "1B-1"
            },
            {
                "registrants": 47021,
                "scheduledInitial": 521,
                "scheduledBooster": 332,
                "atLeastOneShot": 43926,
                "fullyVaccinated": 42289,
                "phase": "1A"
            },
            {
                "registrants": 21249,
                "scheduledInitial": 10,
                "scheduledBooster": 21,
                "atLeastOneShot": 20599,
                "fullyVaccinated": 20246,
                "phase": "1B-0A"
            },
            {
                "registrants": 125677,
                "scheduledInitial": 791,
                "scheduledBooster": 938,
                "atLeastOneShot": 116497,
                "fullyVaccinated": 111767,
                "phase": "1B-2"
            },
            {
                "registrants": 26359,
                "scheduledInitial": 202,
                "scheduledBooster": 431,
                "atLeastOneShot": 23398,
                "fullyVaccinated": 21853,
                "phase": "1C-1"
            },
            {
                "registrants": 40613,
                "scheduledInitial": 789,
                "scheduledBooster": 742,
                "atLeastOneShot": 35833,
                "fullyVaccinated": 33444,
                "phase": "1C-2"
            },
            {
                "registrants": 6732,
                "scheduledInitial": 339,
                "scheduledBooster": 127,
                "atLeastOneShot": 5682,
                "fullyVaccinated": 5297,
                "phase": "1B-0B"
            },
            {
                "registrants": 15277,
                "scheduledInitial": 271,
                "scheduledBooster": 264,
                "atLeastOneShot": 13412,
                "fullyVaccinated": 12612,
                "phase": "1B-3B"
            },
            {
                "registrants": 6018,
                "scheduledInitial": 141,
                "scheduledBooster": 125,
                "atLeastOneShot": 5292,
                "fullyVaccinated": 4933,
                "phase": "1B-3A"
            },
            {
                "registrants": 10924,
                "scheduledInitial": 235,
                "scheduledBooster": 126,
                "atLeastOneShot": 9876,
                "fullyVaccinated": 9110,
                "phase": "1B-3C"
            }
        ],
        "updated": 1636577083412
    }
}