{
    "status": "ok",
    "message": "",
    "data": {
        "data": [
            {
                "registrants": 2700,
                "scheduledInitial": 6,
                "scheduledBooster": 7,
                "atLeastOneShot": 2403,
                "fullyVaccinated": 2299,
                "phase": "1B-2"
            },
            {
                "registrants": 1048,
                "scheduledInitial": 2,
                "scheduledBooster": 3,
                "atLeastOneShot": 931,
                "fullyVaccinated": 884,
                "phase": "1B-1"
            },
            {
                "registrants": 401,
                "scheduledInitial": 7,
                "scheduledBooster": 5,
                "atLeastOneShot": 304,
                "fullyVaccinated": 267,
                "phase": "1C-2"
            },
            {
                "registrants": 630,
                "scheduledInitial": 5,
                "scheduledBooster": 6,
                "atLeastOneShot": 524,
                "fullyVaccinated": 466,
                "phase": "1C-1"
            },
            {
                "registrants": 838,
                "scheduledInitial": 12,
                "scheduledBooster": 21,
                "atLeastOneShot": 600,
                "fullyVaccinated": 493,
                "phase": "2"
            },
            {
                "registrants": 329,
                "scheduledInitial": 1,
                "scheduledBooster": 2,
                "atLeastOneShot": 300,
                "fullyVaccinated": 293,
                "phase": "1B-0A"
            },
            {
                "registrants": 387,
                "scheduledInitial": 0,
                "scheduledBooster": 3,
                "atLeastOneShot": 349,
                "fullyVaccinated": 328,
                "phase": "1A"
            },
            {
                "registrants": 180,
                "scheduledInitial": 8,
                "scheduledBooster": 3,
                "atLeastOneShot": 141,
                "fullyVaccinated": 131,
                "phase": "1B-3B"
            },
            {
                "registrants": 85,
                "scheduledInitial": 1,
                "scheduledBooster": 0,
                "atLeastOneShot": 61,
                "fullyVaccinated": 56,
                "phase": "1B-3C"
            },
            {
                "registrants": 51,
                "scheduledInitial": 1,
                "scheduledBooster": 0,
                "atLeastOneShot": 39,
                "fullyVaccinated": 39,
                "phase": "1B-0B"
            },
            {
                "registrants": 55,
                "scheduledInitial": 0,
                "scheduledBooster": 1,
                "atLeastOneShot": 45,
                "fullyVaccinated": 42,
                "phase": "1B-3A"
            }
        ],
        "updated": 1625172282375
    }
}