{
    "status": "ok",
    "message": "",
    "data": {
        "data": [
            {
                "registrants": 1751,
                "scheduledInitial": 63,
                "scheduledBooster": 182,
                "atLeastOneShot": 1120,
                "fullyVaccinated": 775,
                "phase": "2"
            },
            {
                "registrants": 4115,
                "scheduledInitial": 37,
                "scheduledBooster": 106,
                "atLeastOneShot": 3587,
                "fullyVaccinated": 3285,
                "phase": "1B-2"
            },
            {
                "registrants": 165,
                "scheduledInitial": 5,
                "scheduledBooster": 13,
                "atLeastOneShot": 132,
                "fullyVaccinated": 108,
                "phase": "1B-0B"
            },
            {
                "registrants": 439,
                "scheduledInitial": 5,
                "scheduledBooster": 31,
                "atLeastOneShot": 360,
                "fullyVaccinated": 238,
                "phase": "1B-3C"
            },
            {
                "registrants": 658,
                "scheduledInitial": 20,
                "scheduledBooster": 47,
                "atLeastOneShot": 501,
                "fullyVaccinated": 404,
                "phase": "1C-2"
            },
            {
                "registrants": 706,
                "scheduledInitial": 3,
                "scheduledBooster": 22,
                "atLeastOneShot": 628,
                "fullyVaccinated": 563,
                "phase": "1A"
            },
            {
                "registrants": 544,
                "scheduledInitial": 14,
                "scheduledBooster": 37,
                "atLeastOneShot": 411,
                "fullyVaccinated": 329,
                "phase": "1B-3B"
            },
            {
                "registrants": 642,
                "scheduledInitial": 8,
                "scheduledBooster": 52,
                "atLeastOneShot": 536,
                "fullyVaccinated": 434,
                "phase": "1C-1"
            },
            {
                "registrants": 574,
                "scheduledInitial": 1,
                "scheduledBooster": 5,
                "atLeastOneShot": 530,
                "fullyVaccinated": 495,
                "phase": "1B-0A"
            },
            {
                "registrants": 1026,
                "scheduledInitial": 4,
                "scheduledBooster": 22,
                "atLeastOneShot": 882,
                "fullyVaccinated": 804,
                "phase": "1B-1"
            },
            {
                "registrants": 127,
                "scheduledInitial": 0,
                "scheduledBooster": 3,
                "atLeastOneShot": 105,
                "fullyVaccinated": 90,
                "phase": "1B-3A"
            }
        ],
        "updated": 1621284282144
    }
}