{
    "status": "ok",
    "message": "",
    "data": {
        "data": [
            {
                "registrants": 5276,
                "scheduledInitial": 151,
                "scheduledBooster": 417,
                "atLeastOneShot": 4536,
                "fullyVaccinated": 3514,
                "phase": "2"
            },
            {
                "registrants": 4631,
                "scheduledInitial": 39,
                "scheduledBooster": 63,
                "atLeastOneShot": 4222,
                "fullyVaccinated": 3954,
                "phase": "1B-2"
            },
            {
                "registrants": 186,
                "scheduledInitial": 6,
                "scheduledBooster": 4,
                "atLeastOneShot": 161,
                "fullyVaccinated": 137,
                "phase": "1B-3A"
            },
            {
                "registrants": 269,
                "scheduledInitial": 6,
                "scheduledBooster": 10,
                "atLeastOneShot": 233,
                "fullyVaccinated": 215,
                "phase": "1B-0B"
            },
            {
                "registrants": 634,
                "scheduledInitial": 6,
                "scheduledBooster": 17,
                "atLeastOneShot": 547,
                "fullyVaccinated": 428,
                "phase": "1B-3C"
            },
            {
                "registrants": 1146,
                "scheduledInitial": 21,
                "scheduledBooster": 68,
                "atLeastOneShot": 1034,
                "fullyVaccinated": 890,
                "phase": "1C-1"
            },
            {
                "registrants": 916,
                "scheduledInitial": 17,
                "scheduledBooster": 22,
                "atLeastOneShot": 793,
                "fullyVaccinated": 710,
                "phase": "1C-2"
            },
            {
                "registrants": 965,
                "scheduledInitial": 6,
                "scheduledBooster": 15,
                "atLeastOneShot": 895,
                "fullyVaccinated": 833,
                "phase": "1A"
            },
            {
                "registrants": 708,
                "scheduledInitial": 17,
                "scheduledBooster": 17,
                "atLeastOneShot": 601,
                "fullyVaccinated": 530,
                "phase": "1B-3B"
            },
            {
                "registrants": 1247,
                "scheduledInitial": 6,
                "scheduledBooster": 24,
                "atLeastOneShot": 1142,
                "fullyVaccinated": 1066,
                "phase": "1B-1"
            },
            {
                "registrants": 574,
                "scheduledInitial": 0,
                "scheduledBooster": 2,
                "atLeastOneShot": 545,
                "fullyVaccinated": 521,
                "phase": "1B-0A"
            }
        ],
        "updated": 1634589882502
    }
}