{
    "status": "ok",
    "message": "",
    "data": {
        "data": [
            {
                "registrants": 40308,
                "scheduledInitial": 337,
                "scheduledBooster": 632,
                "atLeastOneShot": 33026,
                "fullyVaccinated": 29556,
                "phase": "1B-2"
            },
            {
                "registrants": 13097,
                "scheduledInitial": 35,
                "scheduledBooster": 96,
                "atLeastOneShot": 11109,
                "fullyVaccinated": 10410,
                "phase": "1B-1"
            },
            {
                "registrants": 10505,
                "scheduledInitial": 81,
                "scheduledBooster": 230,
                "atLeastOneShot": 9287,
                "fullyVaccinated": 8536,
                "phase": "1A"
            },
            {
                "registrants": 8287,
                "scheduledInitial": 5,
                "scheduledBooster": 11,
                "atLeastOneShot": 7571,
                "fullyVaccinated": 7170,
                "phase": "1B-0A"
            },
            {
                "registrants": 5701,
                "scheduledInitial": 126,
                "scheduledBooster": 260,
                "atLeastOneShot": 4136,
                "fullyVaccinated": 3528,
                "phase": "1B-3B"
            },
            {
                "registrants": 2034,
                "scheduledInitial": 24,
                "scheduledBooster": 60,
                "atLeastOneShot": 1680,
                "fullyVaccinated": 1473,
                "phase": "1B-3C"
            },
            {
                "registrants": 2554,
                "scheduledInitial": 37,
                "scheduledBooster": 96,
                "atLeastOneShot": 2143,
                "fullyVaccinated": 1907,
                "phase": "1B-0B"
            },
            {
                "registrants": 29261,
                "scheduledInitial": 903,
                "scheduledBooster": 2447,
                "atLeastOneShot": 21858,
                "fullyVaccinated": 17515,
                "phase": "2"
            },
            {
                "registrants": 7236,
                "scheduledInitial": 66,
                "scheduledBooster": 197,
                "atLeastOneShot": 5648,
                "fullyVaccinated": 4841,
                "phase": "1C-1"
            },
            {
                "registrants": 8731,
                "scheduledInitial": 217,
                "scheduledBooster": 404,
                "atLeastOneShot": 6443,
                "fullyVaccinated": 5351,
                "phase": "1C-2"
            },
            {
                "registrants": 2073,
                "scheduledInitial": 38,
                "scheduledBooster": 96,
                "atLeastOneShot": 1616,
                "fullyVaccinated": 1368,
                "phase": "1B-3A"
            }
        ],
        "updated": 1630529082975
    }
}