{
    "status": "ok",
    "message": "",
    "data": {
        "data": [
            {
                "registrants": 36643,
                "scheduledInitial": 1182,
                "scheduledBooster": 7122,
                "atLeastOneShot": 24248,
                "fullyVaccinated": 14014,
                "phase": "1B-2"
            },
            {
                "registrants": 11906,
                "scheduledInitial": 244,
                "scheduledBooster": 603,
                "atLeastOneShot": 9294,
                "fullyVaccinated": 8046,
                "phase": "1B-1"
            },
            {
                "registrants": 9239,
                "scheduledInitial": 178,
                "scheduledBooster": 586,
                "atLeastOneShot": 7501,
                "fullyVaccinated": 6310,
                "phase": "1A"
            },
            {
                "registrants": 8286,
                "scheduledInitial": 58,
                "scheduledBooster": 763,
                "atLeastOneShot": 6841,
                "fullyVaccinated": 5185,
                "phase": "1B-0A"
            },
            {
                "registrants": 12005,
                "scheduledInitial": 1560,
                "scheduledBooster": 1312,
                "atLeastOneShot": 3008,
                "fullyVaccinated": 954,
                "phase": "2"
            },
            {
                "registrants": 1623,
                "scheduledInitial": 142,
                "scheduledBooster": 502,
                "atLeastOneShot": 1059,
                "fullyVaccinated": 492,
                "phase": "1B-0B"
            },
            {
                "registrants": 5620,
                "scheduledInitial": 147,
                "scheduledBooster": 1103,
                "atLeastOneShot": 3230,
                "fullyVaccinated": 1461,
                "phase": "1C-1"
            },
            {
                "registrants": 3822,
                "scheduledInitial": 249,
                "scheduledBooster": 979,
                "atLeastOneShot": 1826,
                "fullyVaccinated": 622,
                "phase": "1B-3B"
            },
            {
                "registrants": 1466,
                "scheduledInitial": 73,
                "scheduledBooster": 284,
                "atLeastOneShot": 871,
                "fullyVaccinated": 503,
                "phase": "1B-3A"
            },
            {
                "registrants": 5750,
                "scheduledInitial": 587,
                "scheduledBooster": 699,
                "atLeastOneShot": 1929,
                "fullyVaccinated": 659,
                "phase": "1C-2"
            },
            {
                "registrants": 1424,
                "scheduledInitial": 60,
                "scheduledBooster": 466,
                "atLeastOneShot": 937,
                "fullyVaccinated": 308,
                "phase": "1B-3C"
            }
        ],
        "updated": 1617828282823
    }
}