{
    "status": "ok",
    "message": "",
    "data": {
        "data": [
            {
                "registrants": 5523,
                "scheduledInitial": 164,
                "scheduledBooster": 752,
                "atLeastOneShot": 4460,
                "fullyVaccinated": 3396,
                "phase": "2"
            },
            {
                "registrants": 7690,
                "scheduledInitial": 65,
                "scheduledBooster": 242,
                "atLeastOneShot": 7015,
                "fullyVaccinated": 6462,
                "phase": "1B-2"
            },
            {
                "registrants": 1582,
                "scheduledInitial": 22,
                "scheduledBooster": 106,
                "atLeastOneShot": 1379,
                "fullyVaccinated": 1202,
                "phase": "1C-1"
            },
            {
                "registrants": 2046,
                "scheduledInitial": 49,
                "scheduledBooster": 166,
                "atLeastOneShot": 1693,
                "fullyVaccinated": 1415,
                "phase": "1C-2"
            },
            {
                "registrants": 1893,
                "scheduledInitial": 13,
                "scheduledBooster": 16,
                "atLeastOneShot": 1725,
                "fullyVaccinated": 1639,
                "phase": "1B-1"
            },
            {
                "registrants": 623,
                "scheduledInitial": 10,
                "scheduledBooster": 27,
                "atLeastOneShot": 522,
                "fullyVaccinated": 451,
                "phase": "1B-3C"
            },
            {
                "registrants": 1760,
                "scheduledInitial": 21,
                "scheduledBooster": 51,
                "atLeastOneShot": 1492,
                "fullyVaccinated": 1340,
                "phase": "1A"
            },
            {
                "registrants": 728,
                "scheduledInitial": 9,
                "scheduledBooster": 42,
                "atLeastOneShot": 619,
                "fullyVaccinated": 535,
                "phase": "1B-3B"
            },
            {
                "registrants": 788,
                "scheduledInitial": 1,
                "scheduledBooster": 1,
                "atLeastOneShot": 751,
                "fullyVaccinated": 728,
                "phase": "1B-0A"
            },
            {
                "registrants": 385,
                "scheduledInitial": 7,
                "scheduledBooster": 20,
                "atLeastOneShot": 334,
                "fullyVaccinated": 292,
                "phase": "1B-0B"
            },
            {
                "registrants": 198,
                "scheduledInitial": 8,
                "scheduledBooster": 12,
                "atLeastOneShot": 162,
                "fullyVaccinated": 144,
                "phase": "1B-3A"
            }
        ],
        "updated": 1632084283013
    }
}