{
    "status": "ok",
    "message": "",
    "data": {
        "data": [
            {
                "registrants": 6028,
                "scheduledInitial": 224,
                "scheduledBooster": 973,
                "atLeastOneShot": 4988,
                "fullyVaccinated": 3660,
                "phase": "1B-2"
            },
            {
                "registrants": 886,
                "scheduledInitial": 63,
                "scheduledBooster": 279,
                "atLeastOneShot": 611,
                "fullyVaccinated": 226,
                "phase": "1C-1"
            },
            {
                "registrants": 859,
                "scheduledInitial": 180,
                "scheduledBooster": 278,
                "atLeastOneShot": 462,
                "fullyVaccinated": 109,
                "phase": "1C-2"
            },
            {
                "registrants": 1593,
                "scheduledInitial": 29,
                "scheduledBooster": 165,
                "atLeastOneShot": 1284,
                "fullyVaccinated": 1005,
                "phase": "1B-1"
            },
            {
                "registrants": 1403,
                "scheduledInitial": 27,
                "scheduledBooster": 322,
                "atLeastOneShot": 1071,
                "fullyVaccinated": 656,
                "phase": "1A"
            },
            {
                "registrants": 1368,
                "scheduledInitial": 18,
                "scheduledBooster": 159,
                "atLeastOneShot": 358,
                "fullyVaccinated": 127,
                "phase": "2"
            },
            {
                "registrants": 308,
                "scheduledInitial": 18,
                "scheduledBooster": 116,
                "atLeastOneShot": 210,
                "fullyVaccinated": 72,
                "phase": "1B-3C"
            },
            {
                "registrants": 390,
                "scheduledInitial": 44,
                "scheduledBooster": 125,
                "atLeastOneShot": 229,
                "fullyVaccinated": 49,
                "phase": "1B-3B"
            },
            {
                "registrants": 782,
                "scheduledInitial": 13,
                "scheduledBooster": 85,
                "atLeastOneShot": 690,
                "fullyVaccinated": 493,
                "phase": "1B-0A"
            },
            {
                "registrants": 137,
                "scheduledInitial": 12,
                "scheduledBooster": 54,
                "atLeastOneShot": 102,
                "fullyVaccinated": 36,
                "phase": "1B-0B"
            },
            {
                "registrants": 105,
                "scheduledInitial": 11,
                "scheduledBooster": 33,
                "atLeastOneShot": 72,
                "fullyVaccinated": 27,
                "phase": "1B-3A"
            }
        ],
        "updated": 1616877882859
    }
}