{
    "status": "ok",
    "message": "",
    "data": {
        "data": [
            {
                "registrants": 4224,
                "scheduledInitial": 13,
                "scheduledBooster": 43,
                "atLeastOneShot": 3922,
                "fullyVaccinated": 3757,
                "phase": "1B-2"
            },
            {
                "registrants": 3284,
                "scheduledInitial": 58,
                "scheduledBooster": 249,
                "atLeastOneShot": 2845,
                "fullyVaccinated": 2447,
                "phase": "2"
            },
            {
                "registrants": 2070,
                "scheduledInitial": 2,
                "scheduledBooster": 18,
                "atLeastOneShot": 1933,
                "fullyVaccinated": 1845,
                "phase": "1B-1"
            },
            {
                "registrants": 841,
                "scheduledInitial": 9,
                "scheduledBooster": 12,
                "atLeastOneShot": 719,
                "fullyVaccinated": 688,
                "phase": "1B-3B"
            },
            {
                "registrants": 659,
                "scheduledInitial": 3,
                "scheduledBooster": 7,
                "atLeastOneShot": 608,
                "fullyVaccinated": 577,
                "phase": "1A"
            },
            {
                "registrants": 548,
                "scheduledInitial": 0,
                "scheduledBooster": 1,
                "atLeastOneShot": 525,
                "fullyVaccinated": 516,
                "phase": "1B-0A"
            },
            {
                "registrants": 1080,
                "scheduledInitial": 11,
                "scheduledBooster": 52,
                "atLeastOneShot": 961,
                "fullyVaccinated": 866,
                "phase": "1C-1"
            },
            {
                "registrants": 218,
                "scheduledInitial": 1,
                "scheduledBooster": 3,
                "atLeastOneShot": 186,
                "fullyVaccinated": 172,
                "phase": "1B-3A"
            },
            {
                "registrants": 163,
                "scheduledInitial": 1,
                "scheduledBooster": 2,
                "atLeastOneShot": 145,
                "fullyVaccinated": 142,
                "phase": "1B-0B"
            },
            {
                "registrants": 186,
                "scheduledInitial": 0,
                "scheduledBooster": 4,
                "atLeastOneShot": 167,
                "fullyVaccinated": 155,
                "phase": "1B-3C"
            },
            {
                "registrants": 632,
                "scheduledInitial": 9,
                "scheduledBooster": 12,
                "atLeastOneShot": 541,
                "fullyVaccinated": 508,
                "phase": "1C-2"
            }
        ],
        "updated": 1634935483256
    }
}