{
    "status": "ok",
    "message": "",
    "data": {
        "data": [
            {
                "registrants": 6353,
                "scheduledInitial": 121,
                "scheduledBooster": 160,
                "atLeastOneShot": 5438,
                "fullyVaccinated": 4851,
                "phase": "2"
            },
            {
                "registrants": 7704,
                "scheduledInitial": 35,
                "scheduledBooster": 31,
                "atLeastOneShot": 7159,
                "fullyVaccinated": 6790,
                "phase": "1B-2"
            },
            {
                "registrants": 1769,
                "scheduledInitial": 6,
                "scheduledBooster": 8,
                "atLeastOneShot": 1669,
                "fullyVaccinated": 1611,
                "phase": "1A"
            },
            {
                "registrants": 2613,
                "scheduledInitial": 8,
                "scheduledBooster": 8,
                "atLeastOneShot": 2405,
                "fullyVaccinated": 2291,
                "phase": "1B-1"
            },
            {
                "registrants": 731,
                "scheduledInitial": 9,
                "scheduledBooster": 12,
                "atLeastOneShot": 669,
                "fullyVaccinated": 626,
                "phase": "1B-3C"
            },
            {
                "registrants": 1452,
                "scheduledInitial": 12,
                "scheduledBooster": 23,
                "atLeastOneShot": 1286,
                "fullyVaccinated": 1185,
                "phase": "1C-2"
            },
            {
                "registrants": 1990,
                "scheduledInitial": 15,
                "scheduledBooster": 21,
                "atLeastOneShot": 1746,
                "fullyVaccinated": 1598,
                "phase": "1C-1"
            },
            {
                "registrants": 747,
                "scheduledInitial": 0,
                "scheduledBooster": 2,
                "atLeastOneShot": 721,
                "fullyVaccinated": 693,
                "phase": "1B-0A"
            },
            {
                "registrants": 539,
                "scheduledInitial": 2,
                "scheduledBooster": 6,
                "atLeastOneShot": 484,
                "fullyVaccinated": 448,
                "phase": "1B-3A"
            },
            {
                "registrants": 855,
                "scheduledInitial": 4,
                "scheduledBooster": 7,
                "atLeastOneShot": 764,
                "fullyVaccinated": 708,
                "phase": "1B-3B"
            },
            {
                "registrants": 422,
                "scheduledInitial": 1,
                "scheduledBooster": 7,
                "atLeastOneShot": 374,
                "fullyVaccinated": 337,
                "phase": "1B-0B"
            }
        ],
        "updated": 1660855485009
    }
}