{
    "status": "ok",
    "message": "",
    "data": {
        "data": [
            {
                "registrants": 3075,
                "scheduledInitial": 69,
                "scheduledBooster": 302,
                "atLeastOneShot": 2533,
                "fullyVaccinated": 2069,
                "phase": "1B-1"
            },
            {
                "registrants": 2388,
                "scheduledInitial": 49,
                "scheduledBooster": 263,
                "atLeastOneShot": 1934,
                "fullyVaccinated": 1344,
                "phase": "1B-0A"
            },
            {
                "registrants": 9561,
                "scheduledInitial": 251,
                "scheduledBooster": 1981,
                "atLeastOneShot": 7732,
                "fullyVaccinated": 4795,
                "phase": "1B-2"
            },
            {
                "registrants": 1916,
                "scheduledInitial": 28,
                "scheduledBooster": 184,
                "atLeastOneShot": 1647,
                "fullyVaccinated": 1282,
                "phase": "1A"
            },
            {
                "registrants": 2625,
                "scheduledInitial": 10,
                "scheduledBooster": 92,
                "atLeastOneShot": 686,
                "fullyVaccinated": 244,
                "phase": "2"
            },
            {
                "registrants": 456,
                "scheduledInitial": 60,
                "scheduledBooster": 43,
                "atLeastOneShot": 251,
                "fullyVaccinated": 118,
                "phase": "1B-3B"
            },
            {
                "registrants": 270,
                "scheduledInitial": 14,
                "scheduledBooster": 20,
                "atLeastOneShot": 168,
                "fullyVaccinated": 119,
                "phase": "1B-3A"
            },
            {
                "registrants": 1328,
                "scheduledInitial": 441,
                "scheduledBooster": 63,
                "atLeastOneShot": 448,
                "fullyVaccinated": 202,
                "phase": "1C-2"
            },
            {
                "registrants": 1832,
                "scheduledInitial": 415,
                "scheduledBooster": 239,
                "atLeastOneShot": 901,
                "fullyVaccinated": 357,
                "phase": "1C-1"
            },
            {
                "registrants": 126,
                "scheduledInitial": 13,
                "scheduledBooster": 65,
                "atLeastOneShot": 72,
                "fullyVaccinated": 2,
                "phase": "1B-0B"
            },
            {
                "registrants": 213,
                "scheduledInitial": 35,
                "scheduledBooster": 38,
                "atLeastOneShot": 131,
                "fullyVaccinated": 37,
                "phase": "1B-3C"
            }
        ],
        "updated": 1616532282364
    }
}