{
    "status": "ok",
    "message": "",
    "data": {
        "data": [
            {
                "registrants": 24416,
                "scheduledInitial": 1002,
                "scheduledBooster": 4912,
                "atLeastOneShot": 19133,
                "fullyVaccinated": 12211,
                "phase": "1B-2"
            },
            {
                "registrants": 4386,
                "scheduledInitial": 529,
                "scheduledBooster": 1492,
                "atLeastOneShot": 2558,
                "fullyVaccinated": 740,
                "phase": "1C-2"
            },
            {
                "registrants": 7767,
                "scheduledInitial": 168,
                "scheduledBooster": 426,
                "atLeastOneShot": 6376,
                "fullyVaccinated": 5438,
                "phase": "1B-1"
            },
            {
                "registrants": 4570,
                "scheduledInitial": 280,
                "scheduledBooster": 1551,
                "atLeastOneShot": 3084,
                "fullyVaccinated": 841,
                "phase": "1C-1"
            },
            {
                "registrants": 6971,
                "scheduledInitial": 110,
                "scheduledBooster": 486,
                "atLeastOneShot": 6114,
                "fullyVaccinated": 5131,
                "phase": "1A"
            },
            {
                "registrants": 7044,
                "scheduledInitial": 901,
                "scheduledBooster": 1242,
                "atLeastOneShot": 2551,
                "fullyVaccinated": 707,
                "phase": "2"
            },
            {
                "registrants": 597,
                "scheduledInitial": 53,
                "scheduledBooster": 124,
                "atLeastOneShot": 402,
                "fullyVaccinated": 247,
                "phase": "1B-0B"
            },
            {
                "registrants": 3658,
                "scheduledInitial": 26,
                "scheduledBooster": 233,
                "atLeastOneShot": 3286,
                "fullyVaccinated": 2834,
                "phase": "1B-0A"
            },
            {
                "registrants": 2060,
                "scheduledInitial": 124,
                "scheduledBooster": 1001,
                "atLeastOneShot": 1376,
                "fullyVaccinated": 261,
                "phase": "1B-3B"
            },
            {
                "registrants": 769,
                "scheduledInitial": 45,
                "scheduledBooster": 207,
                "atLeastOneShot": 544,
                "fullyVaccinated": 268,
                "phase": "1B-3A"
            },
            {
                "registrants": 1234,
                "scheduledInitial": 54,
                "scheduledBooster": 503,
                "atLeastOneShot": 846,
                "fullyVaccinated": 206,
                "phase": "1B-3C"
            }
        ],
        "updated": 1618173883054
    }
}