{
    "status": "ok",
    "message": "",
    "data": {
        "data": [
            {
                "registrants": 10984,
                "scheduledInitial": 53,
                "scheduledBooster": 114,
                "atLeastOneShot": 9728,
                "fullyVaccinated": 8818,
                "phase": "1C-1"
            },
            {
                "registrants": 21527,
                "scheduledInitial": 531,
                "scheduledBooster": 1431,
                "atLeastOneShot": 17726,
                "fullyVaccinated": 14683,
                "phase": "2"
            },
            {
                "registrants": 31512,
                "scheduledInitial": 113,
                "scheduledBooster": 204,
                "atLeastOneShot": 28974,
                "fullyVaccinated": 27328,
                "phase": "1B-2"
            },
            {
                "registrants": 1262,
                "scheduledInitial": 27,
                "scheduledBooster": 83,
                "atLeastOneShot": 1094,
                "fullyVaccinated": 910,
                "phase": "1B-0B"
            },
            {
                "registrants": 9988,
                "scheduledInitial": 113,
                "scheduledBooster": 241,
                "atLeastOneShot": 8634,
                "fullyVaccinated": 7816,
                "phase": "1C-2"
            },
            {
                "registrants": 3718,
                "scheduledInitial": 33,
                "scheduledBooster": 74,
                "atLeastOneShot": 3212,
                "fullyVaccinated": 2948,
                "phase": "1B-3B"
            },
            {
                "registrants": 13269,
                "scheduledInitial": 27,
                "scheduledBooster": 45,
                "atLeastOneShot": 12241,
                "fullyVaccinated": 11661,
                "phase": "1B-1"
            },
            {
                "registrants": 2976,
                "scheduledInitial": 39,
                "scheduledBooster": 83,
                "atLeastOneShot": 2712,
                "fullyVaccinated": 2459,
                "phase": "1B-3C"
            },
            {
                "registrants": 5139,
                "scheduledInitial": 1,
                "scheduledBooster": 9,
                "atLeastOneShot": 4944,
                "fullyVaccinated": 4780,
                "phase": "1B-0A"
            },
            {
                "registrants": 9455,
                "scheduledInitial": 59,
                "scheduledBooster": 112,
                "atLeastOneShot": 8811,
                "fullyVaccinated": 8383,
                "phase": "1A"
            },
            {
                "registrants": 1402,
                "scheduledInitial": 20,
                "scheduledBooster": 45,
                "atLeastOneShot": 1221,
                "fullyVaccinated": 1108,
                "phase": "1B-3A"
            }
        ],
        "updated": 1637873083556
    }
}