{
    "status": "ok",
    "message": "",
    "data": {
        "data": [
            {
                "registrants": 10164,
                "scheduledInitial": 67,
                "scheduledBooster": 172,
                "atLeastOneShot": 8838,
                "fullyVaccinated": 7251,
                "phase": "1C-1"
            },
            {
                "registrants": 31063,
                "scheduledInitial": 112,
                "scheduledBooster": 284,
                "atLeastOneShot": 28199,
                "fullyVaccinated": 25746,
                "phase": "1B-2"
            },
            {
                "registrants": 992,
                "scheduledInitial": 7,
                "scheduledBooster": 33,
                "atLeastOneShot": 856,
                "fullyVaccinated": 731,
                "phase": "1B-0B"
            },
            {
                "registrants": 9562,
                "scheduledInitial": 106,
                "scheduledBooster": 269,
                "atLeastOneShot": 8099,
                "fullyVaccinated": 6978,
                "phase": "1C-2"
            },
            {
                "registrants": 3535,
                "scheduledInitial": 45,
                "scheduledBooster": 99,
                "atLeastOneShot": 2961,
                "fullyVaccinated": 2598,
                "phase": "1B-3B"
            },
            {
                "registrants": 18619,
                "scheduledInitial": 394,
                "scheduledBooster": 1114,
                "atLeastOneShot": 14763,
                "fullyVaccinated": 11899,
                "phase": "2"
            },
            {
                "registrants": 12222,
                "scheduledInitial": 16,
                "scheduledBooster": 54,
                "atLeastOneShot": 11173,
                "fullyVaccinated": 10499,
                "phase": "1B-1"
            },
            {
                "registrants": 2758,
                "scheduledInitial": 20,
                "scheduledBooster": 59,
                "atLeastOneShot": 2495,
                "fullyVaccinated": 2126,
                "phase": "1B-3C"
            },
            {
                "registrants": 5128,
                "scheduledInitial": 0,
                "scheduledBooster": 16,
                "atLeastOneShot": 4920,
                "fullyVaccinated": 4672,
                "phase": "1B-0A"
            },
            {
                "registrants": 8784,
                "scheduledInitial": 47,
                "scheduledBooster": 109,
                "atLeastOneShot": 8162,
                "fullyVaccinated": 7652,
                "phase": "1A"
            },
            {
                "registrants": 1304,
                "scheduledInitial": 17,
                "scheduledBooster": 44,
                "atLeastOneShot": 1124,
                "fullyVaccinated": 1003,
                "phase": "1B-3A"
            }
        ],
        "updated": 1630356282910
    }
}