{
    "status": "ok",
    "message": "",
    "data": {
        "data": [
            {
                "registrants": 345942,
                "scheduledInitial": 7345,
                "scheduledBooster": 14605,
                "atLeastOneShot": 292716,
                "fullyVaccinated": 256912,
                "phase": "2"
            },
            {
                "registrants": 134741,
                "scheduledInitial": 355,
                "scheduledBooster": 649,
                "atLeastOneShot": 122500,
                "fullyVaccinated": 117772,
                "phase": "1B-1"
            },
            {
                "registrants": 98015,
                "scheduledInitial": 776,
                "scheduledBooster": 1569,
                "atLeastOneShot": 85073,
                "fullyVaccinated": 78864,
                "phase": "1C-1"
            },
            {
                "registrants": 96862,
                "scheduledInitial": 1273,
                "scheduledBooster": 1687,
                "atLeastOneShot": 85401,
                "fullyVaccinated": 79440,
                "phase": "1C-2"
            },
            {
                "registrants": 114397,
                "scheduledInitial": 540,
                "scheduledBooster": 668,
                "atLeastOneShot": 107342,
                "fullyVaccinated": 103438,
                "phase": "1A"
            },
            {
                "registrants": 56232,
                "scheduledInitial": 18,
                "scheduledBooster": 59,
                "atLeastOneShot": 53994,
                "fullyVaccinated": 52737,
                "phase": "1B-0A"
            },
            {
                "registrants": 22855,
                "scheduledInitial": 216,
                "scheduledBooster": 328,
                "atLeastOneShot": 20555,
                "fullyVaccinated": 19234,
                "phase": "1B-0B"
            },
            {
                "registrants": 359294,
                "scheduledInitial": 1801,
                "scheduledBooster": 2347,
                "atLeastOneShot": 332794,
                "fullyVaccinated": 318345,
                "phase": "1B-2"
            },
            {
                "registrants": 17851,
                "scheduledInitial": 250,
                "scheduledBooster": 288,
                "atLeastOneShot": 15726,
                "fullyVaccinated": 14654,
                "phase": "1B-3A"
            },
            {
                "registrants": 44528,
                "scheduledInitial": 543,
                "scheduledBooster": 706,
                "atLeastOneShot": 38922,
                "fullyVaccinated": 36427,
                "phase": "1B-3B"
            },
            {
                "registrants": 29484,
                "scheduledInitial": 241,
                "scheduledBooster": 293,
                "atLeastOneShot": 27100,
                "fullyVaccinated": 25371,
                "phase": "1B-3C"
            }
        ],
        "updated": 1666903490527
    }
}