{
    "status": "ok",
    "message": "",
    "data": {
        "data": [
            {
                "registrants": 87084,
                "scheduledInitial": 494,
                "scheduledBooster": 2755,
                "atLeastOneShot": 13015,
                "fullyVaccinated": 5219,
                "phase": "2"
            },
            {
                "registrants": 81485,
                "scheduledInitial": 1489,
                "scheduledBooster": 8464,
                "atLeastOneShot": 68765,
                "fullyVaccinated": 53565,
                "phase": "1A"
            },
            {
                "registrants": 55717,
                "scheduledInitial": 611,
                "scheduledBooster": 21073,
                "atLeastOneShot": 47852,
                "fullyVaccinated": 21325,
                "phase": "1B-0A"
            },
            {
                "registrants": 294353,
                "scheduledInitial": 15559,
                "scheduledBooster": 81136,
                "atLeastOneShot": 206626,
                "fullyVaccinated": 90482,
                "phase": "1B-2"
            },
            {
                "registrants": 57940,
                "scheduledInitial": 2195,
                "scheduledBooster": 6577,
                "atLeastOneShot": 22799,
                "fullyVaccinated": 8410,
                "phase": "1C-1"
            },
            {
                "registrants": 51682,
                "scheduledInitial": 2178,
                "scheduledBooster": 3662,
                "atLeastOneShot": 11661,
                "fullyVaccinated": 4285,
                "phase": "1C-2"
            },
            {
                "registrants": 101548,
                "scheduledInitial": 1687,
                "scheduledBooster": 9136,
                "atLeastOneShot": 79341,
                "fullyVaccinated": 62308,
                "phase": "1B-1"
            },
            {
                "registrants": 6888,
                "scheduledInitial": 524,
                "scheduledBooster": 3126,
                "atLeastOneShot": 4362,
                "fullyVaccinated": 725,
                "phase": "1B-0B"
            },
            {
                "registrants": 17909,
                "scheduledInitial": 2800,
                "scheduledBooster": 3061,
                "atLeastOneShot": 7102,
                "fullyVaccinated": 2428,
                "phase": "1B-3B"
            },
            {
                "registrants": 9812,
                "scheduledInitial": 800,
                "scheduledBooster": 1264,
                "atLeastOneShot": 5902,
                "fullyVaccinated": 3556,
                "phase": "1B-3A"
            },
            {
                "registrants": 16416,
                "scheduledInitial": 1889,
                "scheduledBooster": 2059,
                "atLeastOneShot": 6108,
                "fullyVaccinated": 2033,
                "phase": "1B-3C"
            }
        ],
        "updated": 1616791482768
    }
}