{
    "status": "ok",
    "message": "",
    "data": {
        "data": [
            {
                "registrants": 6652,
                "scheduledInitial": 68,
                "scheduledBooster": 745,
                "atLeastOneShot": 5747,
                "fullyVaccinated": 4426,
                "phase": "1B-2"
            },
            {
                "registrants": 2083,
                "scheduledInitial": 7,
                "scheduledBooster": 113,
                "atLeastOneShot": 1919,
                "fullyVaccinated": 1645,
                "phase": "1A"
            },
            {
                "registrants": 1622,
                "scheduledInitial": 32,
                "scheduledBooster": 399,
                "atLeastOneShot": 1329,
                "fullyVaccinated": 819,
                "phase": "1C-2"
            },
            {
                "registrants": 2467,
                "scheduledInitial": 61,
                "scheduledBooster": 929,
                "atLeastOneShot": 1711,
                "fullyVaccinated": 636,
                "phase": "2"
            },
            {
                "registrants": 2783,
                "scheduledInitial": 10,
                "scheduledBooster": 94,
                "atLeastOneShot": 2321,
                "fullyVaccinated": 2065,
                "phase": "1B-1"
            },
            {
                "registrants": 714,
                "scheduledInitial": 16,
                "scheduledBooster": 147,
                "atLeastOneShot": 553,
                "fullyVaccinated": 358,
                "phase": "1B-3B"
            },
            {
                "registrants": 268,
                "scheduledInitial": 0,
                "scheduledBooster": 28,
                "atLeastOneShot": 229,
                "fullyVaccinated": 176,
                "phase": "1B-3C"
            },
            {
                "registrants": 2211,
                "scheduledInitial": 26,
                "scheduledBooster": 326,
                "atLeastOneShot": 1793,
                "fullyVaccinated": 1184,
                "phase": "1C-1"
            },
            {
                "registrants": 1131,
                "scheduledInitial": 1,
                "scheduledBooster": 16,
                "atLeastOneShot": 1055,
                "fullyVaccinated": 982,
                "phase": "1B-0A"
            },
            {
                "registrants": 280,
                "scheduledInitial": 7,
                "scheduledBooster": 52,
                "atLeastOneShot": 233,
                "fullyVaccinated": 162,
                "phase": "1B-3A"
            },
            {
                "registrants": 150,
                "scheduledInitial": 1,
                "scheduledBooster": 53,
                "atLeastOneShot": 120,
                "fullyVaccinated": 52,
                "phase": "1B-0B"
            }
        ],
        "updated": 1619642684016
    }
}