{
    "status": "ok",
    "message": "",
    "data": {
        "data": [
            {
                "registrants": 789,
                "scheduledInitial": 1,
                "scheduledBooster": 8,
                "atLeastOneShot": 724,
                "fullyVaccinated": 680,
                "phase": "1B-1"
            },
            {
                "registrants": 403,
                "scheduledInitial": 16,
                "scheduledBooster": 11,
                "atLeastOneShot": 339,
                "fullyVaccinated": 308,
                "phase": "1C-2"
            },
            {
                "registrants": 2625,
                "scheduledInitial": 34,
                "scheduledBooster": 49,
                "atLeastOneShot": 2423,
                "fullyVaccinated": 2266,
                "phase": "1B-2"
            },
            {
                "registrants": 280,
                "scheduledInitial": 0,
                "scheduledBooster": 1,
                "atLeastOneShot": 268,
                "fullyVaccinated": 258,
                "phase": "1B-0A"
            },
            {
                "registrants": 1444,
                "scheduledInitial": 65,
                "scheduledBooster": 91,
                "atLeastOneShot": 1191,
                "fullyVaccinated": 1001,
                "phase": "2"
            },
            {
                "registrants": 99,
                "scheduledInitial": 0,
                "scheduledBooster": 5,
                "atLeastOneShot": 81,
                "fullyVaccinated": 74,
                "phase": "1B-3A"
            },
            {
                "registrants": 532,
                "scheduledInitial": 5,
                "scheduledBooster": 8,
                "atLeastOneShot": 496,
                "fullyVaccinated": 469,
                "phase": "1A"
            },
            {
                "registrants": 131,
                "scheduledInitial": 2,
                "scheduledBooster": 5,
                "atLeastOneShot": 121,
                "fullyVaccinated": 110,
                "phase": "1B-0B"
            },
            {
                "registrants": 113,
                "scheduledInitial": 5,
                "scheduledBooster": 3,
                "atLeastOneShot": 99,
                "fullyVaccinated": 86,
                "phase": "1B-3C"
            },
            {
                "registrants": 646,
                "scheduledInitial": 1,
                "scheduledBooster": 7,
                "atLeastOneShot": 572,
                "fullyVaccinated": 530,
                "phase": "1C-1"
            },
            {
                "registrants": 308,
                "scheduledInitial": 8,
                "scheduledBooster": 9,
                "atLeastOneShot": 268,
                "fullyVaccinated": 246,
                "phase": "1B-3B"
            }
        ],
        "updated": 1639428283620
    }
}