{
    "status": "ok",
    "message": "",
    "data": {
        "data": [
            {
                "registrants": 683,
                "scheduledInitial": 3,
                "scheduledBooster": 21,
                "atLeastOneShot": 584,
                "fullyVaccinated": 526,
                "phase": "1B-1"
            },
            {
                "registrants": 284,
                "scheduledInitial": 15,
                "scheduledBooster": 47,
                "atLeastOneShot": 215,
                "fullyVaccinated": 152,
                "phase": "1C-2"
            },
            {
                "registrants": 2403,
                "scheduledInitial": 43,
                "scheduledBooster": 139,
                "atLeastOneShot": 2065,
                "fullyVaccinated": 1794,
                "phase": "1B-2"
            },
            {
                "registrants": 282,
                "scheduledInitial": 0,
                "scheduledBooster": 3,
                "atLeastOneShot": 260,
                "fullyVaccinated": 245,
                "phase": "1B-0A"
            },
            {
                "registrants": 651,
                "scheduledInitial": 27,
                "scheduledBooster": 168,
                "atLeastOneShot": 460,
                "fullyVaccinated": 251,
                "phase": "2"
            },
            {
                "registrants": 77,
                "scheduledInitial": 1,
                "scheduledBooster": 8,
                "atLeastOneShot": 60,
                "fullyVaccinated": 52,
                "phase": "1B-3A"
            },
            {
                "registrants": 442,
                "scheduledInitial": 7,
                "scheduledBooster": 18,
                "atLeastOneShot": 406,
                "fullyVaccinated": 369,
                "phase": "1A"
            },
            {
                "registrants": 93,
                "scheduledInitial": 2,
                "scheduledBooster": 11,
                "atLeastOneShot": 79,
                "fullyVaccinated": 66,
                "phase": "1B-0B"
            },
            {
                "registrants": 70,
                "scheduledInitial": 2,
                "scheduledBooster": 7,
                "atLeastOneShot": 51,
                "fullyVaccinated": 38,
                "phase": "1B-3C"
            },
            {
                "registrants": 475,
                "scheduledInitial": 7,
                "scheduledBooster": 40,
                "atLeastOneShot": 411,
                "fullyVaccinated": 340,
                "phase": "1C-1"
            },
            {
                "registrants": 229,
                "scheduledInitial": 6,
                "scheduledBooster": 25,
                "atLeastOneShot": 189,
                "fullyVaccinated": 155,
                "phase": "1B-3B"
            }
        ],
        "updated": 1621370682229
    }
}