{
    "status": "ok",
    "message": "",
    "data": {
        "data": [
            {
                "registrants": 2491,
                "scheduledInitial": 23,
                "scheduledBooster": 75,
                "atLeastOneShot": 2044,
                "fullyVaccinated": 1832,
                "phase": "1C-1"
            },
            {
                "registrants": 13107,
                "scheduledInitial": 92,
                "scheduledBooster": 177,
                "atLeastOneShot": 11702,
                "fullyVaccinated": 11133,
                "phase": "1B-2"
            },
            {
                "registrants": 4190,
                "scheduledInitial": 14,
                "scheduledBooster": 34,
                "atLeastOneShot": 3688,
                "fullyVaccinated": 3545,
                "phase": "1B-1"
            },
            {
                "registrants": 1205,
                "scheduledInitial": 26,
                "scheduledBooster": 35,
                "atLeastOneShot": 1000,
                "fullyVaccinated": 929,
                "phase": "1B-3B"
            },
            {
                "registrants": 1684,
                "scheduledInitial": 0,
                "scheduledBooster": 1,
                "atLeastOneShot": 1605,
                "fullyVaccinated": 1571,
                "phase": "1B-0A"
            },
            {
                "registrants": 6838,
                "scheduledInitial": 266,
                "scheduledBooster": 505,
                "atLeastOneShot": 5177,
                "fullyVaccinated": 4374,
                "phase": "2"
            },
            {
                "registrants": 2646,
                "scheduledInitial": 68,
                "scheduledBooster": 102,
                "atLeastOneShot": 2155,
                "fullyVaccinated": 1957,
                "phase": "1C-2"
            },
            {
                "registrants": 2837,
                "scheduledInitial": 26,
                "scheduledBooster": 46,
                "atLeastOneShot": 2521,
                "fullyVaccinated": 2375,
                "phase": "1A"
            },
            {
                "registrants": 463,
                "scheduledInitial": 12,
                "scheduledBooster": 22,
                "atLeastOneShot": 384,
                "fullyVaccinated": 343,
                "phase": "1B-0B"
            },
            {
                "registrants": 563,
                "scheduledInitial": 5,
                "scheduledBooster": 18,
                "atLeastOneShot": 470,
                "fullyVaccinated": 418,
                "phase": "1B-3C"
            },
            {
                "registrants": 591,
                "scheduledInitial": 14,
                "scheduledBooster": 16,
                "atLeastOneShot": 489,
                "fullyVaccinated": 456,
                "phase": "1B-3A"
            }
        ],
        "updated": 1626986682033
    }
}